observable/__init__.py
observable/__version__.py
observable/core.py
observable-1.0.3.dist-info/DESCRIPTION.rst
observable-1.0.3.dist-info/METADATA
observable-1.0.3.dist-info/RECORD
observable-1.0.3.dist-info/WHEEL
observable-1.0.3.dist-info/metadata.json
observable-1.0.3.dist-info/top_level.txt
tests/__init__.py
tests/test_core.py
